APIMakeSens-1.4.12.data/data/data/colors_by_variable.json
MakeSens/MakeSens.py
MakeSens/__init__.py
MakeSens/__main__.py
MakeSens/colors_by_variable.json
APIMakeSens-1.4.12.dist-info/LICENSE
APIMakeSens-1.4.12.dist-info/METADATA
APIMakeSens-1.4.12.dist-info/WHEEL
APIMakeSens-1.4.12.dist-info/entry_points.txt
APIMakeSens-1.4.12.dist-info/top_level.txt
APIMakeSens-1.4.12.dist-info/RECORD
