Metadata-Version: 2.1
Name: APIMakeSens
Version: 1.4.12
Summary: MakeSense API
Home-page: https://github.com/MakeSens-Data/MakeSensAPI_Python
Author: MakeSens
Author-email: makesens19@gmail.com
License: GNU General Public License v3.0
Classifier: Programming Language :: Python :: 3
Classifier: Programming Language :: Python :: 3.9
License-File: LICENSE
Requires-Dist: pandas
Requires-Dist: requests
Requires-Dist: datetime
